Metadata-Version: 2.1
Name: delta2D-numcodecs
Version: 0.1.0
Summary: Numcodecs implementation of delta filter in 2D.
Home-page: https://github.com/AllenNeuralDynamics/delta2D-numcodecs
Author: Alessio Buccino
Author-email: alessiop.buccino@gmail.com
License: UNKNOWN
Platform: UNKNOWN
Classifier: Programming Language :: Python :: 3
Classifier: License :: OSI Approved :: MIT License
Classifier: Operating System :: OS Independent
License-File: LICENSE
